setup.py
slikio/__init__.py
slikio/slikio.py
slikio/test.py
slikio_python.egg-info/PKG-INFO
slikio_python.egg-info/SOURCES.txt
slikio_python.egg-info/dependency_links.txt
slikio_python.egg-info/requires.txt
slikio_python.egg-info/top_level.txt