Metadata-Version: 1.0
Name: slikio-python
Version: 0.0.3
Summary: Python library for SlikIO - Charts for developers
Home-page: http://slik.io
Author: Daniel Brodsky, SlikIO
Author-email: daniel@slik.io
License: MIT
Keywords: slikio,SlikIO,slik.io,charts,graphs,django chart templates
Platform: UNKNOWN
